featboostx/__init__.py
featboostx/feat_boost_classifier.py
featboostx/feat_boost_estimator.py
featboostx/feat_boost_regressor.py
featboostx-0.1.0rc2.dist-info/METADATA
featboostx-0.1.0rc2.dist-info/WHEEL
featboostx-0.1.0rc2.dist-info/top_level.txt
featboostx-0.1.0rc2.dist-info/RECORD
