Metadata-Version: 2.2
Name: featboostx
Version: 0.1.0rc2
Summary: A Python package for the FeatBoost-X feature selection algorithm
Home-page: https://github.com/O-T-O-Z/FeatBoost-X
Author: Ömer Tarik Özyilmaz & Ahmad Alsahaf
Author-email: o.t.ozyilmaz@umcg.nl
Keywords: Feature Selection,Gradient Boosting,FeatBoost-X
Classifier: Development Status :: 3 - Alpha
Classifier: Intended Audience :: Developers
Classifier: Topic :: Software Development :: Build Tools
Classifier: Programming Language :: Python :: 3.11
Requires-Python: >=3.10, <4
Requires-Dist: numpy<2.0,>=1.26
Requires-Dist: shap~=0.45
Requires-Dist: lifelines<1.0,>=0.26
Requires-Dist: pytest<8.0,>=7.0
Requires-Dist: xgboost<3.0,>=2.0
Requires-Dist: scipy<2.0,>=1.13
Dynamic: author
Dynamic: author-email
Dynamic: classifier
Dynamic: description
Dynamic: description-content-type
Dynamic: home-page
Dynamic: keywords
Dynamic: requires-dist
Dynamic: requires-python
Dynamic: summary
